Workbook
Name cid: Table2[Id]
Name HSN_No: Table5[HSN_No]

Sheet Customers
F7: Id | G7: Name | H7: Email | I7: Address
F8: 1 | G8: Camila | H8: camila@Gmail.com | I8: Mumbai
F9: 2 | G9: Alexander | H9: alexander@Gmail.com | I9: Mumbai
F10: 3 | G10: Liam | H10: liam@Gmail.com | I10: Mumbai
F11: 4 | G11: Evelyn | H11: evelyn@Gmail.com | I11: Kolkata
F12: 5 | G12: Michael | H12: michael@Gmail.com | I12: Delhi
F13: 6 | G13: Chloe | H13: chloe@Gmail.com | I13: Bangalore
F14: 7 | G14: Nicholas | H14: nicholas@Gmail.com | I14: Kolkata
F15: 8 | G15: Olivia | H15: olivia@Gmail.com | I15: Bangalore
F16: 9 | G16: Aiden | H16: aiden@Gmail.com | I16: Mumbai
F17: 10 | G17: Harper | H17: harper@Gmail.com | I17: Chennai
F18: 11 | G18: Madison | H18: madison@Gmail.com | I18: Kolkata
F19: 12 | G19: Carter | H19: carter@Gmail.com | I19: Kolkata
... F28: 21 | G28: Lily | H28: lily@Gmail.com | I28: Chennai

Sheet Products
F8: HSN_No | G8: Products Name | H8: Sales | I8: Cost | J8: Profit
F9: N001 | G9: Bookcases | H9: 261.96 | I9: =Table5[[#This Row],[Sales]]-Table5[[#This Row],[Profit]] -> 220.0464 | J9: 41.9136
F10: N002 | G10: Chairs | H10: 731.94 | I10: =Table5[[#This Row],[Sales]]-Table5[[#This Row],[Profit]] -> 512.358 | J10: 219.582
F11: N003 | G11: Labels | H11: 14.62 | I11: =Table5[[#This Row],[Sales]]-Table5[[#This Row],[Profit]] -> 7.7486 | J11: 6.8714
F12: N004 | G12: Tables | H12: 957.5775 | I12: =Table5[[#This Row],[Sales]]-Table5[[#This Row],[Profit]] -> 574.5465 | J12: 383.031
F13: N005 | G13: Storage | H13: 22.368 | I13: =Table5[[#This Row],[Sales]]-Table5[[#This Row],[Profit]] -> 19.8516 | J13: 2.5164
F14: N006 | G14: Furnishings | H14: 48.86 | I14: =Table5[[#This Row],[Sales]]-Table5[[#This Row],[Profit]] -> 34.6906 | J14: 14.1694
F15: N007 | G15: Art | H15: 7.28 | I15: =Table5[[#This Row],[Sales]]-Table5[[#This Row],[Profit]] -> 5.3144 | J15: 1.9656
F16: N008 | G16: Phones | H16: 907.152 | I16: =Table5[[#This Row],[Sales]]-Table5[[#This Row],[Profit]] -> 816.4368 | J16: 90.7152
F17: N009 | G17: Binders | H17: 18.504 | I17: =Table5[[#This Row],[Sales]]-Table5[[#This Row],[Profit]] -> 12.7215 | J17: 5.7825
F18: N010 | G18: Appliances | H18: 114.9 | I18: =Table5[[#This Row],[Sales]]-Table5[[#This Row],[Profit]] -> 80.43 | J18: 34.47
F19: N011 | G19: Paper | H19: 1706.184 | I19: =Table5[[#This Row],[Sales]]-Table5[[#This Row],[Profit]] -> 1620.8748 | J19: 85.3092
F20: N012 | G20: Binders | H20: 911.424 | I20: =Table5[[#This Row],[Sales]]-Table5[[#This Row],[Profit]] -> 843.0672 | J20: 68.3568

Sheet Vendors
F8: HSN No | G8: Products Name | H8: Vendors Name | I8: City | J8: State | K8: Region | L8: Phone Number
F9: N001 | G9: Bookcases | H9: Harper | I9: Henderson | J9: Kentucky | K9: South | L9: 016#######
F10: N002 | G10: Chairs | H10: Madison | I10: Henderson | J10: Kentucky | K10: South | L10: 017#######
F11: N003 | G11: Labels | H11: Carter | I11: Los Angeles | J11: California | K11: West | L11: 018#######
F12: N004 | G12: Tables | H12: Mia | I12: Fort Lauderdale | J12: Florida | K12: South | L12: 019#######
F13: N005 | G13: Storage | H13: Lucas | I13: Fort Lauderdale | J13: Florida | K13: South | L13: 011#######
F14: N006 | G14: Furnishings | H14: Abigail | I14: Los Angeles | J14: California | K14: West | L14: 012#######
F15: N007 | G15: Art | H15: Joseph | I15: Los Angeles | J15: California | K15: West | L15: 013#######
F16: N008 | G16: Phones | H16: William | I16: Los Angeles | J16: California | K16: West | L16: 014#######
F17: N009 | G17: Binders | H17: Andrew | I17: Los Angeles | J17: California | K17: West | L17: 015#######
F18: N010 | G18: Appliances | H18: Sophia | I18: Los Angeles | J18: California | K18: West | L18: 0133######
F19: N011 | G19: Paper | H19: Avery | I19: Los Angeles | J19: California | K19: West | L19: 0177######
F20: N012 | G20: Binders | H20: Lily | I20: Los Angeles | J20: California | K20: West | L20: 0158######

Sheet Purchase
F8: HSN No | G8: Products Name | H8: Vender | I8: Date | J8: Units | K8: Cost | L8: Amount
F9: N003 | G9: =IFERROR(VLOOKUP(Table8[[#This Row],[HSN No]],Table5[#All],2,0),"") -> Labels | H9: =IFERROR(VLOOKUP(Table8[[#This Row],[HSN No]],Table7[#All],3,0),"") -> Carter | I9: 46032 | J9: 23 | K9: =IFERROR(VLOOKUP(Table8[[#This Row],[HSN No]],Products!F8:J19,4,0),"") -> 7.7486 | L9: =IFERROR((Table8[[#This Row],[Units]]*Table8[[#This Row],[Cost]]),"") -> 178.2178
F10: N004 | G10: =IFERROR(VLOOKUP(Table8[[#This Row],[HSN No]],Table5[#All],2,0),"") -> Tables | H10: =IFERROR(VLOOKUP(Table8[[#This Row],[HSN No]],Table7[#All],3,0),"") -> Mia | I10: 46033 | J10: 43 | K10: =IFERROR(VLOOKUP(Table8[[#This Row],[HSN No]],Products!F9:J20,4,0),"") -> 574.5465 | L10: =IFERROR((Table8[[#This Row],[Units]]*Table8[[#This Row],[Cost]]),"") -> 24705.499
F11: N006 | G11: =IFERROR(VLOOKUP(Table8[[#This Row],[HSN No]],Table5[#All],2,0),"") -> Furnishings | H11: =IFERROR(VLOOKUP(Table8[[#This Row],[HSN No]],Table7[#All],3,0),"") -> Abigail | I11: 46034 | J11: 33 | K11: =IFERROR(VLOOKUP(Table8[[#This Row],[HSN No]],Products!F10:J21,4,0),"") -> 34.6906 | L11: =IFERROR((Table8[[#This Row],[Units]]*Table8[[#This Row],[Cost]]),"") -> 1144.7898
F12: N008 | G12: =IFERROR(VLOOKUP(Table8[[#This Row],[HSN No]],Table5[#All],2,0),"") -> Phones | H12: =IFERROR(VLOOKUP(Table8[[#This Row],[HSN No]],Table7[#All],3,0),"") -> William | I12: 46035 | J12: 45 | K12: =IFERROR(VLOOKUP(Table8[[#This Row],[HSN No]],Products!F11:J22,4,0),"") -> 816.4368 | L12: =IFERROR((Table8[[#This Row],[Units]]*Table8[[#This Row],[Cost]]),"") -> 36739.656
F13: N005 | G13: =IFERROR(VLOOKUP(Table8[[#This Row],[HSN No]],Table5[#All],2,0),"") -> Storage | H13: =IFERROR(VLOOKUP(Table8[[#This Row],[HSN No]],Table7[#All],3,0),"") -> Lucas | I13: 46036 | J13: 24 | K13: =IFERROR(VLOOKUP(Table8[[#This Row],[HSN No]],Products!F12:J23,4,0),"") -> 19.8516 | L13: =IFERROR((Table8[[#This Row],[Units]]*Table8[[#This Row],[Cost]]),"") -> 476.4384
F14: N007 | G14: =IFERROR(VLOOKUP(Table8[[#This Row],[HSN No]],Table5[#All],2,0),"") -> Art | H14: =IFERROR(VLOOKUP(Table8[[#This Row],[HSN No]],Table7[#All],3,0),"") -> Joseph | I14: 46037 | J14: 24 | K14: =IFERROR(VLOOKUP(Table8[[#This Row],[HSN No]],Products!F13:J24,4,0),"") -> 5.3144 | L14: =IFERROR((Table8[[#This Row],[Units]]*Table8[[#This Row],[Cost]]),"") -> 127.5456
F15: N006 | G15: =IFERROR(VLOOKUP(Table8[[#This Row],[HSN No]],Table5[#All],2,0),"") -> Furnishings | H15: =IFERROR(VLOOKUP(Table8[[#This Row],[HSN No]],Table7[#All],3,0),"") -> Abigail | I15: 46038 | J15: 24 | K15: =IFERROR(VLOOKUP(Table8[[#This Row],[HSN No]],Products!F14:J25,4,0),"") -> 34.6906 | L15: =IFERROR((Table8[[#This Row],[Units]]*Table8[[#This Row],[Cost]]),"") -> 832.5744
G16: =IFERROR(VLOOKUP(Table8[[#This Row],[HSN No]],Table5[#All],2,0),"") | H16: =IFERROR(VLOOKUP(Table8[[#This Row],[HSN No]],Table7[#All],3,0),"") | K16: =IFERROR(VLOOKUP(Table8[[#This Row],[HSN No]],Products!F15:J26,4,0),"") | L16: =IFERROR((Table8[[#This Row],[Units]]*Table8[[#This Row],[Cost]]),"")
G17: =IFERROR(VLOOKUP(Table8[[#This Row],[HSN No]],Table5[#All],2,0),"") | H17: =IFERROR(VLOOKUP(Table8[[#This Row],[HSN No]],Table7[#All],3,0),"") | K17: =IFERROR(VLOOKUP(Table8[[#This Row],[HSN No]],Products!F16:J27,4,0),"") | L17: =IFERROR((Table8[[#This Row],[Units]]*Table8[[#This Row],[Cost]]),"")
G18: =IFERROR(VLOOKUP(Table8[[#This Row],[HSN No]],Table5[#All],2,0),"") | H18: =IFERROR(VLOOKUP(Table8[[#This Row],[HSN No]],Table7[#All],3,0),"") | K18: =IFERROR(VLOOKUP(Table8[[#This Row],[HSN No]],Products!F17:J28,4,0),"") | L18: =IFERROR((Table8[[#This Row],[Units]]*Table8[[#This Row],[Cost]]),"")
G19: =IFERROR(VLOOKUP(Table8[[#This Row],[HSN No]],Table5[#All],2,0),"") | H19: =IFERROR(VLOOKUP(Table8[[#This Row],[HSN No]],Table7[#All],3,0),"") | K19: =IFERROR(VLOOKUP(Table8[[#This Row],[HSN No]],Products!F18:J29,4,0),"") | L19: =IFERROR((Table8[[#This Row],[Units]]*Table8[[#This Row],[Cost]]),"")
G20: =IFERROR(VLOOKUP(Table8[[#This Row],[HSN No]],Table5[#All],2,0),"") | H20: =IFERROR(VLOOKUP(Table8[[#This Row],[HSN No]],Table7[#All],3,0),"") | K20: =IFERROR(VLOOKUP(Table8[[#This Row],[HSN No]],Products!F19:J30,4,0),"") | L20: =IFERROR((Table8[[#This Row],[Units]]*Table8[[#This Row],[Cost]]),"")
G21: =IFERROR(VLOOKUP(Table8[[#This Row],[HSN No]],Table5[#All],2,0),"") | H21: =IFERROR(VLOOKUP(Table8[[#This Row],[HSN No]],Table7[#All],3,0),"") | K21: =IFERROR(VLOOKUP(Table8[[#This Row],[HSN No]],Products!F20:J31,4,0),"") | L21: =IFERROR((Table8[[#This Row],[Units]]*Table8[[#This Row],[Cost]]),"")
G22: =IFERROR(VLOOKUP(Table8[[#This Row],[HSN No]],Table5[#All],2,0),"") | H22: =IFERROR(VLOOKUP(Table8[[#This Row],[HSN No]],Table7[#All],3,0),"") | K22: =IFERROR(VLOOKUP(Table8[[#This Row],[HSN No]],Products!F21:J32,4,0),"") | L22: =IFERROR((Table8[[#This Row],[Units]]*Table8[[#This Row],[Cost]]),"")
G23: =IFERROR(VLOOKUP(Table8[[#This Row],[HSN No]],Table5[#All],2,0),"") | H23: =IFERROR(VLOOKUP(Table8[[#This Row],[HSN No]],Table7[#All],3,0),"") | K23: =IFERROR(VLOOKUP(Table8[[#This Row],[HSN No]],Products!F22:J33,4,0),"") | L23: =IFERROR((Table8[[#This Row],[Units]]*Table8[[#This Row],[Cost]]),"")
G24: =IFERROR(VLOOKUP(Table8[[#This Row],[HSN No]],Table5[#All],2,0),"") | H24: =IFERROR(VLOOKUP(Table8[[#This Row],[HSN No]],Table7[#All],3,0),"") | K24: =IFERROR(VLOOKUP(Table8[[#This Row],[HSN No]],Products!F23:J34,4,0),"") | L24: =IFERROR((Table8[[#This Row],[Units]]*Table8[[#This Row],[Cost]]),"")

Sheet Sales
F7: Customer Id | G7: Customer Name | H7: HSN No | I7: Product Name | J7: Date | K7: Stock(Unit) | L7: Units | M7: Price | N7: Amount
F8: 5 | G8: =IFERROR(VLOOKUP(Table9[[#This Row],[Customer Id]],Table2[#All],2,0),"") -> Michael | H8: N004 | I8: =IFERROR(VLOOKUP(Table9[[#This Row],[HSN No]],Table5[#All],2,0),"") -> Tables | J8: 46122 | K8: =IFERROR(VLOOKUP(Table9[[#This Row],[HSN No]],Table10[#All],6,0),"") -> 13 | L8: 6 | M8: =IFERROR(VLOOKUP(Table9[[#This Row],[HSN No]],Table5[#All],3,0),"") -> 957.5775 | N8: =IFERROR((Table9[[#This Row],[Price]]*Table9[[#This Row],[Units]]),"") -> 5745.465
F9: 1 | G9: =IFERROR(VLOOKUP(Table9[[#This Row],[Customer Id]],Table2[#All],2,0),"") -> Camila | H9: N007 | I9: =IFERROR(VLOOKUP(Table9[[#This Row],[HSN No]],Table5[#All],2,0),"") -> Art | J9: 46123 | K9: =IFERROR(VLOOKUP(Table9[[#This Row],[HSN No]],Table10[#All],6,0),"") -> 4 | L9: 7 | M9: =IFERROR(VLOOKUP(Table9[[#This Row],[HSN No]],Table5[#All],3,0),"") -> 7.28 | N9: =IFERROR((Table9[[#This Row],[Price]]*Table9[[#This Row],[Units]]),"") -> 50.96
F10: 6 | G10: =IFERROR(VLOOKUP(Table9[[#This Row],[Customer Id]],Table2[#All],2,0),"") -> Chloe | H10: N007 | I10: =IFERROR(VLOOKUP(Table9[[#This Row],[HSN No]],Table5[#All],2,0),"") -> Art | J10: 46124 | K10: =IFERROR(VLOOKUP(Table9[[#This Row],[HSN No]],Table10[#All],6,0),"") -> 4 | L10: 7 | M10: =IFERROR(VLOOKUP(Table9[[#This Row],[HSN No]],Table5[#All],3,0),"") -> 7.28 | N10: =IFERROR((Table9[[#This Row],[Price]]*Table9[[#This Row],[Units]]),"") -> 50.96
F11: 6 | G11: =IFERROR(VLOOKUP(Table9[[#This Row],[Customer Id]],Table2[#All],2,0),"") -> Chloe | H11: N007 | I11: =IFERROR(VLOOKUP(Table9[[#This Row],[HSN No]],Table5[#All],2,0),"") -> Art | J11: 46125 | K11: =IFERROR(VLOOKUP(Table9[[#This Row],[HSN No]],Table10[#All],6,0),"") -> 4 | L11: 5 | M11: =IFERROR(VLOOKUP(Table9[[#This Row],[HSN No]],Table5[#All],3,0),"") -> 7.28 | N11: =IFERROR((Table9[[#This Row],[Price]]*Table9[[#This Row],[Units]]),"") -> 36.4
F12: 10 | G12: =IFERROR(VLOOKUP(Table9[[#This Row],[Customer Id]],Table2[#All],2,0),"") -> Harper | H12: N008 | I12: =IFERROR(VLOOKUP(Table9[[#This Row],[HSN No]],Table5[#All],2,0),"") -> Phones | J12: 46126 | K12: =IFERROR(VLOOKUP(Table9[[#This Row],[HSN No]],Table10[#All],6,0),"") -> 20 | L12: 3 | M12: =IFERROR(VLOOKUP(Table9[[#This Row],[HSN No]],Table5[#All],3,0),"") -> 907.152 | N12: =IFERROR((Table9[[#This Row],[Price]]*Table9[[#This Row],[Units]]),"") -> 2721.456
F13: 6 | G13: =IFERROR(VLOOKUP(Table9[[#This Row],[Customer Id]],Table2[#All],2,0),"") -> Chloe | H13: N012 | I13: =IFERROR(VLOOKUP(Table9[[#This Row],[HSN No]],Table5[#All],2,0),"") -> Binders | J13: 46127 | K13: =IFERROR(VLOOKUP(Table9[[#This Row],[HSN No]],Table10[#All],6,0),"") -> 19 | L13: 4 | M13: =IFERROR(VLOOKUP(Table9[[#This Row],[HSN No]],Table5[#All],3,0),"") -> 911.424 | N13: =IFERROR((Table9[[#This Row],[Price]]*Table9[[#This Row],[Units]]),"") -> 3645.696
F14: 1 | G14: =IFERROR(VLOOKUP(Table9[[#This Row],[Customer Id]],Table2[#All],2,0),"") -> Camila | H14: N003 | I14: =IFERROR(VLOOKUP(Table9[[#This Row],[HSN No]],Table5[#All],2,0),"") -> Labels | J14: 46128 | K14: =IFERROR(VLOOKUP(Table9[[#This Row],[HSN No]],Table10[#All],6,0),"") -> 17 | L14: 6 | M14: =IFERROR(VLOOKUP(Table9[[#This Row],[HSN No]],Table5[#All],3,0),"") -> 14.62 | N14: =IFERROR((Table9[[#This Row],[Price]]*Table9[[#This Row],[Units]]),"") -> 87.72
F15: 2 | G15: =IFERROR(VLOOKUP(Table9[[#This Row],[Customer Id]],Table2[#All],2,0),"") -> Alexander | H15: N004 | I15: =IFERROR(VLOOKUP(Table9[[#This Row],[HSN No]],Table5[#All],2,0),"") -> Tables | J15: 46129 | K15: =IFERROR(VLOOKUP(Table9[[#This Row],[HSN No]],Table10[#All],6,0),"") -> 13 | L15: 4 | M15: =IFERROR(VLOOKUP(Table9[[#This Row],[HSN No]],Table5[#All],3,0),"") -> 957.5775 | N15: =IFERROR((Table9[[#This Row],[Price]]*Table9[[#This Row],[Units]]),"") -> 3830.31
G16: =IFERROR(VLOOKUP(Table9[[#This Row],[Customer Id]],Table2[#All],2,0),"") | I16: =IFERROR(VLOOKUP(Table9[[#This Row],[HSN No]],Table5[#All],2,0),"") | K16: =IFERROR(VLOOKUP(Table9[[#This Row],[HSN No]],Table10[#All],6,0),"") -> 0 | M16: =IFERROR(VLOOKUP(Table9[[#This Row],[HSN No]],Table5[#All],3,0),"") | N16: =IFERROR((Table9[[#This Row],[Price]]*Table9[[#This Row],[Units]]),"")
G17: =IFERROR(VLOOKUP(Table9[[#This Row],[Customer Id]],Table2[#All],2,0),"") | I17: =IFERROR(VLOOKUP(Table9[[#This Row],[HSN No]],Table5[#All],2,0),"") | K17: =IFERROR(VLOOKUP(Table9[[#This Row],[HSN No]],Table10[#All],6,0),"") -> 0 | M17: =IFERROR(VLOOKUP(Table9[[#This Row],[HSN No]],Table5[#All],3,0),"") | N17: =IFERROR((Table9[[#This Row],[Price]]*Table9[[#This Row],[Units]]),"")
G18: =IFERROR(VLOOKUP(Table9[[#This Row],[Customer Id]],Table2[#All],2,0),"") | I18: =IFERROR(VLOOKUP(Table9[[#This Row],[HSN No]],Table5[#All],2,0),"") | K18: =IFERROR(VLOOKUP(Table9[[#This Row],[HSN No]],Table10[#All],6,0),"") -> 0 | M18: =IFERROR(VLOOKUP(Table9[[#This Row],[HSN No]],Table5[#All],3,0),"") | N18: =IFERROR((Table9[[#This Row],[Price]]*Table9[[#This Row],[Units]]),"")
G19: =IFERROR(VLOOKUP(Table9[[#This Row],[Customer Id]],Table2[#All],2,0),"") | I19: =IFERROR(VLOOKUP(Table9[[#This Row],[HSN No]],Table5[#All],2,0),"") | K19: =IFERROR(VLOOKUP(Table9[[#This Row],[HSN No]],Table10[#All],6,0),"") -> 0 | M19: =IFERROR(VLOOKUP(Table9[[#This Row],[HSN No]],Table5[#All],3,0),"") | N19: =IFERROR((Table9[[#This Row],[Price]]*Table9[[#This Row],[Units]]),"")
G20: =IFERROR(VLOOKUP(Table9[[#This Row],[Customer Id]],Table2[#All],2,0),"") | I20: =IFERROR(VLOOKUP(Table9[[#This Row],[HSN No]],Table5[#All],2,0),"") | K20: =IFERROR(VLOOKUP(Table9[[#This Row],[HSN No]],Table10[#All],6,0),"") -> 0 | M20: =IFERROR(VLOOKUP(Table9[[#This Row],[HSN No]],Table5[#All],3,0),"") | N20: =IFERROR((Table9[[#This Row],[Price]]*Table9[[#This Row],[Units]]),"")
G21: =IFERROR(VLOOKUP(Table9[[#This Row],[Customer Id]],Table2[#All],2,0),"") | I21: =IFERROR(VLOOKUP(Table9[[#This Row],[HSN No]],Table5[#All],2,0),"") | K21: =IFERROR(VLOOKUP(Table9[[#This Row],[HSN No]],Table10[#All],6,0),"") -> 0 | M21: =IFERROR(VLOOKUP(Table9[[#This Row],[HSN No]],Table5[#All],3,0),"") | N21: =IFERROR((Table9[[#This Row],[Price]]*Table9[[#This Row],[Units]]),"")
G22: =IFERROR(VLOOKUP(Table9[[#This Row],[Customer Id]],Table2[#All],2,0),"") | I22: =IFERROR(VLOOKUP(Table9[[#This Row],[HSN No]],Table5[#All],2,0),"") | K22: =IFERROR(VLOOKUP(Table9[[#This Row],[HSN No]],Table10[#All],6,0),"") -> 0 | M22: =IFERROR(VLOOKUP(Table9[[#This Row],[HSN No]],Table5[#All],3,0),"") | N22: =IFERROR((Table9[[#This Row],[Price]]*Table9[[#This Row],[Units]]),"")
G23: =IFERROR(VLOOKUP(Table9[[#This Row],[Customer Id]],Table2[#All],2,0),"") | I23: =IFERROR(VLOOKUP(Table9[[#This Row],[HSN No]],Table5[#All],2,0),"") | K23: =IFERROR(VLOOKUP(Table9[[#This Row],[HSN No]],Table10[#All],6,0),"") -> 0 | M23: =IFERROR(VLOOKUP(Table9[[#This Row],[HSN No]],Table5[#All],3,0),"") | N23: =IFERROR((Table9[[#This Row],[Price]]*Table9[[#This Row],[Units]]),"")
G24: =IFERROR(VLOOKUP(Table9[[#This Row],[Customer Id]],Table2[#All],2,0),"") | I24: =IFERROR(VLOOKUP(Table9[[#This Row],[HSN No]],Table5[#All],2,0),"") | K24: =IFERROR(VLOOKUP(Table9[[#This Row],[HSN No]],Table10[#All],6,0),"") -> 0 | M24: =IFERROR(VLOOKUP(Table9[[#This Row],[HSN No]],Table5[#All],3,0),"") | N24: =IFERROR((Table9[[#This Row],[Price]]*Table9[[#This Row],[Units]]),"")

Sheet Inventory
F7: HSN No | G7: Product Name | H7: Cost | I7: P Units | J7: S Units | K7: Stock | L7: Stock Amt | M7: Notification
F8: =IFERROR((Products!F9),"") -> N001 | G8: =IFERROR((Products!G9),"") -> Bookcases | H8: =IFERROR((Products!H9),"") -> 261.96 | I8: =SUMIF(Products!G9:G20,Inventory!G8:G19,Table8[Units]) -> 23 | J8: =SUMIF(Table9[Product Name],Table10[[#This Row],[Product Name]],Table9[Units]) -> 0 | K8: =Table10[[#This Row],[P Units]]-Table10[[#This Row],[S Units]] -> 23 | L8: =Table10[[#This Row],[Cost]]*Table10[[#This Row],[Stock]] -> 6025.08 | M8: =IFERROR(IF(Table10[[#This Row],[Stock]]<10,"📞 "&Table10[[#This Row],[Product Name]]&" Needs to re-order! PH"&VLOOKUP(Table10[[#This Row],[HSN No]],Vendors!F7:L21,7,0),""),"")
F9: =IFERROR((Products!F10),"") -> N002 | G9: =IFERROR((Products!G10),"") -> Chairs | H9: =IFERROR((Products!H10),"") -> 731.94 | I9: =SUMIF(Products!G10:G21,Inventory!G9:G20,Table8[Units]) -> 23 | J9: =SUMIF(Table9[Product Name],Table10[[#This Row],[Product Name]],Table9[Units]) -> 0 | K9: =Table10[[#This Row],[P Units]]-Table10[[#This Row],[S Units]] -> 23 | L9: =Table10[[#This Row],[Cost]]*Table10[[#This Row],[Stock]] -> 16834.62 | M9: =IFERROR(IF(Table10[[#This Row],[Stock]]<10,"📞 "&Table10[[#This Row],[Product Name]]&" Needs to re-order! PH"&VLOOKUP(Table10[[#This Row],[HSN No]],Vendors!F8:L22,7,0),""),"")
F10: =IFERROR((Products!F11),"") -> N003 | G10: =IFERROR((Products!G11),"") -> Labels | H10: =IFERROR((Products!H11),"") -> 14.62 | I10: =SUMIF(Products!G11:G22,Inventory!G10:G21,Table8[Units]) -> 23 | J10: =SUMIF(Table9[Product Name],Table10[[#This Row],[Product Name]],Table9[Units]) -> 6 | K10: =Table10[[#This Row],[P Units]]-Table10[[#This Row],[S Units]] -> 17 | L10: =Table10[[#This Row],[Cost]]*Table10[[#This Row],[Stock]] -> 248.54 | M10: =IFERROR(IF(Table10[[#This Row],[Stock]]<10,"📞 "&Table10[[#This Row],[Product Name]]&" Needs to re-order! PH"&VLOOKUP(Table10[[#This Row],[HSN No]],Vendors!F9:L23,7,0),""),"")
F11: =IFERROR((Products!F12),"") -> N004 | G11: =IFERROR((Products!G12),"") -> Tables | H11: =IFERROR((Products!H12),"") -> 957.5775 | I11: =SUMIF(Products!G12:G23,Inventory!G11:G22,Table8[Units]) -> 23 | J11: =SUMIF(Table9[Product Name],Table10[[#This Row],[Product Name]],Table9[Units]) -> 10 | K11: =Table10[[#This Row],[P Units]]-Table10[[#This Row],[S Units]] -> 13 | L11: =Table10[[#This Row],[Cost]]*Table10[[#This Row],[Stock]] -> 12448.507 | M11: =IFERROR(IF(Table10[[#This Row],[Stock]]<10,"📞 "&Table10[[#This Row],[Product Name]]&" Needs to re-order! PH"&VLOOKUP(Table10[[#This Row],[HSN No]],Vendors!F10:L24,7,0),""),"")
F12: =IFERROR((Products!F13),"") -> N005 | G12: =IFERROR((Products!G13),"") -> Storage | H12: =IFERROR((Products!H13),"") -> 22.368 | I12: =SUMIF(Products!G13:G24,Inventory!G12:G23,Table8[Units]) -> 23 | J12: =SUMIF(Table9[Product Name],Table10[[#This Row],[Product Name]],Table9[Units]) -> 0 | K12: =Table10[[#This Row],[P Units]]-Table10[[#This Row],[S Units]] -> 23 | L12: =Table10[[#This Row],[Cost]]*Table10[[#This Row],[Stock]] -> 514.464 | M12: =IFERROR(IF(Table10[[#This Row],[Stock]]<10,"📞 "&Table10[[#This Row],[Product Name]]&" Needs to re-order! PH"&VLOOKUP(Table10[[#This Row],[HSN No]],Vendors!F11:L25,7,0),""),"")
F13: =IFERROR((Products!F14),"") -> N006 | G13: =IFERROR((Products!G14),"") -> Furnishings | H13: =IFERROR((Products!H14),"") -> 48.86 | I13: =SUMIF(Products!G14:G25,Inventory!G13:G24,Table8[Units]) -> 23 | J13: =SUMIF(Table9[Product Name],Table10[[#This Row],[Product Name]],Table9[Units]) -> 0 | K13: =Table10[[#This Row],[P Units]]-Table10[[#This Row],[S Units]] -> 23 | L13: =Table10[[#This Row],[Cost]]*Table10[[#This Row],[Stock]] -> 1123.78 | M13: =IFERROR(IF(Table10[[#This Row],[Stock]]<10,"📞 "&Table10[[#This Row],[Product Name]]&" Needs to re-order! PH"&VLOOKUP(Table10[[#This Row],[HSN No]],Vendors!F12:L26,7,0),""),"")
F14: =IFERROR((Products!F15),"") -> N007 | G14: =IFERROR((Products!G15),"") -> Art | H14: =IFERROR((Products!H15),"") -> 7.28 | I14: =SUMIF(Products!G15:G26,Inventory!G14:G25,Table8[Units]) -> 23 | J14: =SUMIF(Table9[Product Name],Table10[[#This Row],[Product Name]],Table9[Units]) -> 19 | K14: =Table10[[#This Row],[P Units]]-Table10[[#This Row],[S Units]] -> 4 | L14: =Table10[[#This Row],[Cost]]*Table10[[#This Row],[Stock]] -> 29.12 | M14: =IFERROR(IF(Table10[[#This Row],[Stock]]<10,"📞 "&Table10[[#This Row],[Product Name]]&" Needs to re-order! PH"&VLOOKUP(Table10[[#This Row],[HSN No]],Vendors!F13:L27,7,0),""),"") -> 📞 Art Needs to re-order! PH013#######
F15: =IFERROR((Products!F16),"") -> N008 | G15: =IFERROR((Products!G16),"") -> Phones | H15: =IFERROR((Products!H16),"") -> 907.152 | I15: =SUMIF(Products!G16:G27,Inventory!G15:G26,Table8[Units]) -> 23 | J15: =SUMIF(Table9[Product Name],Table10[[#This Row],[Product Name]],Table9[Units]) -> 3 | K15: =Table10[[#This Row],[P Units]]-Table10[[#This Row],[S Units]] -> 20 | L15: =Table10[[#This Row],[Cost]]*Table10[[#This Row],[Stock]] -> 18143.04 | M15: =IFERROR(IF(Table10[[#This Row],[Stock]]<10,"📞 "&Table10[[#This Row],[Product Name]]&" Needs to re-order! PH"&VLOOKUP(Table10[[#This Row],[HSN No]],Vendors!F14:L28,7,0),""),"")
F16: =IFERROR((Products!F17),"") -> N009 | G16: =IFERROR((Products!G17),"") -> Binders | H16: =IFERROR((Products!H17),"") -> 18.504 | I16: =SUMIF(Products!G17:G28,Inventory!G16:G27,Table8[Units]) -> 68 | J16: =SUMIF(Table9[Product Name],Table10[[#This Row],[Product Name]],Table9[Units]) -> 4 | K16: =Table10[[#This Row],[P Units]]-Table10[[#This Row],[S Units]] -> 64 | L16: =Table10[[#This Row],[Cost]]*Table10[[#This Row],[Stock]] -> 1184.256 | M16: =IFERROR(IF(Table10[[#This Row],[Stock]]<10,"📞 "&Table10[[#This Row],[Product Name]]&" Needs to re-order! PH"&VLOOKUP(Table10[[#This Row],[HSN No]],Vendors!F15:L29,7,0),""),"")
F17: =IFERROR((Products!F18),"") -> N010 | G17: =IFERROR((Products!G18),"") -> Appliances | H17: =IFERROR((Products!H18),"") -> 114.9 | I17: =SUMIF(Products!G18:G29,Inventory!G17:G28,Table8[Units]) -> 23 | J17: =SUMIF(Table9[Product Name],Table10[[#This Row],[Product Name]],Table9[Units]) -> 0 | K17: =Table10[[#This Row],[P Units]]-Table10[[#This Row],[S Units]] -> 23 | L17: =Table10[[#This Row],[Cost]]*Table10[[#This Row],[Stock]] -> 2642.7 | M17: =IFERROR(IF(Table10[[#This Row],[Stock]]<10,"📞 "&Table10[[#This Row],[Product Name]]&" Needs to re-order! PH"&VLOOKUP(Table10[[#This Row],[HSN No]],Vendors!F16:L30,7,0),""),"")
F18: =IFERROR((Products!F19),"") -> N011 | G18: =IFERROR((Products!G19),"") -> Paper | H18: =IFERROR((Products!H19),"") -> 1706.184 | I18: =SUMIF(Products!G19:G30,Inventory!G18:G29,Table8[Units]) -> 23 | J18: =SUMIF(Table9[Product Name],Table10[[#This Row],[Product Name]],Table9[Units]) -> 0 | K18: =Table10[[#This Row],[P Units]]-Table10[[#This Row],[S Units]] -> 23 | L18: =Table10[[#This Row],[Cost]]*Table10[[#This Row],[Stock]] -> 39242.232 | M18: =IFERROR(IF(Table10[[#This Row],[Stock]]<10,"📞 "&Table10[[#This Row],[Product Name]]&" Needs to re-order! PH"&VLOOKUP(Table10[[#This Row],[HSN No]],Vendors!F17:L31,7,0),""),"")
F19: =IFERROR((Products!F20),"") -> N012 | G19: =IFERROR((Products!G20),"") -> Binders | H19: =IFERROR((Products!H20),"") -> 911.424 | I19: =SUMIF(Products!G20:G31,Inventory!G19:G30,Table8[Units]) -> 23 | J19: =SUMIF(Table9[Product Name],Table10[[#This Row],[Product Name]],Table9[Units]) -> 4 | K19: =Table10[[#This Row],[P Units]]-Table10[[#This Row],[S Units]] -> 19 | L19: =Table10[[#This Row],[Cost]]*Table10[[#This Row],[Stock]] -> 17317.056 | M19: =IFERROR(IF(Table10[[#This Row],[Stock]]<10,"📞 "&Table10[[#This Row],[Product Name]]&" Needs to re-order! PH"&VLOOKUP(Table10[[#This Row],[HSN No]],Vendors!F18:L32,7,0),""),"")
... F30: =IFERROR((Products!F31),"") -> 0 | G30: =IFERROR((Products!G31),"") -> 0 | H30: =IFERROR((Products!H31),"") -> 0 | I30: =SUMIF(Products!G31:G42,Inventory!G30:G41,Table8[Units]) -> 0 | J30: =SUMIF(Table9[Product Name],Table10[[#This Row],[Product Name]],Table9[Units]) -> 0 | K30: =Table10[[#This Row],[P Units]]-Table10[[#This Row],[S Units]] -> 0 | L30: =Table10[[#This Row],[Cost]]*Table10[[#This Row],[Stock]] -> 0 | M30: =IFERROR(IF(Table10[[#This Row],[Stock]]<10,"📞 "&Table10[[#This Row],[Product Name]]&" Needs to re-order! PH"&VLOOKUP(Table10[[#This Row],[HSN No]],Vendors!F29:L43,7,0),""),"")

Sheet New Entry

Sheet Dashboard
O16: =IFERROR(VLOOKUP(Inventory!F8,Table10[#All],8,0),"")
O17: =IFERROR(VLOOKUP(Inventory!F9,Table10[#All],8,0),"")
O18: =IFERROR(VLOOKUP(Inventory!F10,Table10[#All],8,0),"")
O19: =IFERROR(VLOOKUP(Inventory!F11,Table10[#All],8,0),"")
O20: =IFERROR(VLOOKUP(Inventory!F12,Table10[#All],8,0),"")
O21: =IFERROR(VLOOKUP(Inventory!F13,Table10[#All],8,0),"")
O22: =IFERROR(VLOOKUP(Inventory!F14,Table10[#All],8,0),"") -> 📞 Art Needs to re-order! PH013#######
O23: =IFERROR(VLOOKUP(Inventory!F15,Table10[#All],8,0),"")
O24: =IFERROR(VLOOKUP(Inventory!F16,Table10[#All],8,0),"")
O25: =IFERROR(VLOOKUP(Inventory!F17,Table10[#All],8,0),"")
O26: =IFERROR(VLOOKUP(Inventory!F18,Table10[#All],8,0),"")
O27: =IFERROR(VLOOKUP(Inventory!F19,Table10[#All],8,0),"")
... O29: =IFERROR(VLOOKUP(Inventory!F21,Table10[#All],8,0),"")

Sheet Pivots
A1: Count of Name | C1: Total Customer | E1: Row Labels | F1: Sum of S Units
A2: 21 | C2: =GETPIVOTDATA("Name",$A$1) -> 21 | E2: Art | F2: 19
E3: Binders | F3: 8
A4: Count of Prsducts Name | C4: Total Products | E4: Labels | F4: 6
A5: 12 | C5: =GETPIVOTDATA("Prsducts Name",$A$4) -> 12 | E5: Phones | F5: 3
E6: Tables | F6: 10
A7: Sum of Amount | C7: Purchase Amount | E7: Grand Total | F7: 46
A8: 64204.721 | C8: =GETPIVOTDATA("Amount",$A$7) -> 64204.721
E10: Row Labels | F10: Sum of Amount
A11: Sum of Amount | C11: Sales Amt | E11: Alexander | F11: 3830.31
A12: 16168.967 | C12: =GETPIVOTDATA("Amount",$A$11) -> 16168.967 | E12: Camila | F12: 138.68
E13: Chloe | F13: 3733.056
A14: Sum of Stock Amt | C14: Stock Amt | E14: Harper | F14: 2721.456
A15: 115753.4 | C15: =GETPIVOTDATA("Stock Amt",$A$14) -> 115753.4 | E15: Michael | F15: 5745.465
E16: Grand Total | F16: 16168.967
C17: p/s
C18: =C15+C12-C8 -> 67717.641
A24: Row Labels | B24: Sum of Stock
A25: Appliances | B25: 23
A26: Art | B26: 4
A27: Binders | B27: 83
A28: Bookcases | B28: 23
A29: Chairs | B29: 23
A30: Furnishings | B30: 23
A31: Labels | B31: 17
A32: Paper | B32: 23
A33: Phones | B33: 20
A34: Storage | B34: 23
A35: Tables | B35: 13
A36: Grand Total | B36: 275
